scid.py
scid-0.3.dist-info/DESCRIPTION.rst
scid-0.3.dist-info/METADATA
scid-0.3.dist-info/RECORD
scid-0.3.dist-info/WHEEL
scid-0.3.dist-info/entry_points.txt
scid-0.3.dist-info/metadata.json
scid-0.3.dist-info/top_level.txt
