Metadata-Version: 2.0
Name: scid
Version: 0.3
Summary: Tool for installing solr config files
Home-page: https://github.com/ryantownshend/solr_config_installer_device
Author: Ryan Townshend
Author-email: citizen.townshend@gmail.com
License: UNKNOWN
Platform: UNKNOWN
Requires-Dist: click (>=6.7)
Requires-Dist: click-log (>=0.2.1)
